pydantic_deep/__init__.py
pydantic_deep/agent.py
pydantic_deep/deps.py
pydantic_deep/types.py
pydantic_deep/processors/__init__.py
pydantic_deep/processors/summarization.py
pydantic_deep/toolsets/__init__.py
pydantic_deep/toolsets/filesystem.py
pydantic_deep/toolsets/skills.py
pydantic_deep/toolsets/subagents.py
pydantic_deep-0.2.9.dist-info/METADATA
pydantic_deep-0.2.9.dist-info/WHEEL
pydantic_deep-0.2.9.dist-info/licenses/LICENSE
pydantic_deep-0.2.9.dist-info/RECORD
