Metadata-Version: 2.4
Name: pydantic-deep
Version: 0.2.9
Summary: Deep Agent framework built on Pydantic-ai with planning, filesystem, and subagent capabilities
Project-URL: Homepage, https://github.com/vstorm-co/pydantic-deepagents
Project-URL: Documentation, https://github.com/vstorm-co/pydantic-deepagents
Project-URL: Repository, https://github.com/vstorm-co/pydantic-deepagents
Project-URL: Issues, https://github.com/vstorm-co/pydantic-deepagents/issues
Author: Pydantic Deep Contributors
License-Expression: MIT
License-File: LICENSE
Classifier: Development Status :: 4 - Beta
Classifier: Intended Audience :: Developers
Classifier: License :: OSI Approved :: MIT License
Classifier: Operating System :: OS Independent
Classifier: Programming Language :: Python
Classifier: Programming Language :: Python :: 3
Classifier: Programming Language :: Python :: 3.10
Classifier: Programming Language :: Python :: 3.11
Classifier: Programming Language :: Python :: 3.12
Classifier: Programming Language :: Python :: 3.13
Classifier: Topic :: Software Development :: Libraries :: Python Modules
Classifier: Typing :: Typed
Requires-Python: >=3.10
Requires-Dist: chardet>=5.2.0
Requires-Dist: fastapi>=0.125.0
Requires-Dist: httpx>=0.28.1
Requires-Dist: prompt-toolkit>=3.0.0
Requires-Dist: pydantic-ai-backend>=0.0.3
Requires-Dist: pydantic-ai-todo>=0.1.0
Requires-Dist: pydantic-ai>=0.1.0
Requires-Dist: pydantic-settings>=2.0.0
Requires-Dist: pydantic>=2.0
Requires-Dist: rich>=13.0.0
Requires-Dist: typer>=0.12.0
Requires-Dist: uvicorn>=0.38.0
Provides-Extra: dev
Requires-Dist: fastapi>=0.124.0; extra == 'dev'
Requires-Dist: pre-commit>=4.5.1; extra == 'dev'
Requires-Dist: pyright>=1.1.407; extra == 'dev'
Requires-Dist: python-multipart>=0.0.21; extra == 'dev'
Requires-Dist: ruff>=0.14.9; extra == 'dev'
Requires-Dist: uvicorn>=0.38.0; extra == 'dev'
Provides-Extra: sandbox
Requires-Dist: pydantic-ai-backend[docker]>=0.0.3; extra == 'sandbox'
